mdka/__init__.py
mdka/mdka.cpython-314t-aarch64-linux-musl.so
mdka-1.6.5.dist-info/METADATA
mdka-1.6.5.dist-info/WHEEL
mdka-1.6.5.dist-info/licenses/LICENSE
mdka.libs/libgcc_s-39080030.so.1
mdka-1.6.5.dist-info/RECORD
