Metadata-Version: 2.4
Name: mdka
Version: 1.6.5
Classifier: Programming Language :: Rust
Classifier: Programming Language :: Python :: Implementation :: CPython
Classifier: Programming Language :: Python :: Implementation :: PyPy
Classifier: Intended Audience :: Developers
Classifier: Topic :: Text Processing :: Markup
Classifier: Topic :: Documentation
Classifier: Topic :: Software Development :: Libraries
Classifier: Topic :: Utilities
Classifier: Operating System :: OS Independent
License-File: LICENSE
Keywords: html,markdown,parser,conversion
License: Apache-2.0
Requires-Python: >=3.10
